pyairtouch-3.1.0.dist-info/METADATA
pyairtouch-3.1.0.dist-info/WHEEL
pyairtouch-3.1.0.dist-info/entry_points.txt
pyairtouch-3.1.0.dist-info/licenses/LICENSE
pyairtouch/__init__.py
pyairtouch/api.py
pyairtouch/at4/__init__.py
pyairtouch/at4/api.py
pyairtouch/at4/comms/__init__.py
pyairtouch/at4/comms/discovery.py
pyairtouch/at4/comms/hdr.py
pyairtouch/at4/comms/registry.py
pyairtouch/at4/comms/utils.py
pyairtouch/at4/comms/x1FFF10_err_info.py
pyairtouch/at4/comms/x1FFF11_ac_ability.py
pyairtouch/at4/comms/x1FFF12_group_names.py
pyairtouch/at4/comms/x1FFF20_quick_timer.py
pyairtouch/at4/comms/x1FFF30_console_ver.py
pyairtouch/at4/comms/x1F_ext.py
pyairtouch/at4/comms/x2A_group_ctrl.py
pyairtouch/at4/comms/x2B_group_status.py
pyairtouch/at4/comms/x2C_ac_ctrl.py
pyairtouch/at4/comms/x2D_ac_status.py
pyairtouch/at4/comms/x36_ac_timer_ctrl.py
pyairtouch/at4/comms/x37_ac_timer_status.py
pyairtouch/at5/__init__.py
pyairtouch/at5/api.py
pyairtouch/at5/comms/__init__.py
pyairtouch/at5/comms/discovery.py
pyairtouch/at5/comms/hdr.py
pyairtouch/at5/comms/registry.py
pyairtouch/at5/comms/utils.py
pyairtouch/at5/comms/x1FFF10_err_info.py
pyairtouch/at5/comms/x1FFF11_ac_ability.py
pyairtouch/at5/comms/x1FFF13_zone_names.py
pyairtouch/at5/comms/x1FFF30_console_ver.py
pyairtouch/at5/comms/x1FFF49_quick_timer.py
pyairtouch/at5/comms/x1F_ext.py
pyairtouch/at5/comms/xC020_zone_ctrl.py
pyairtouch/at5/comms/xC021_zone_status.py
pyairtouch/at5/comms/xC022_ac_ctrl.py
pyairtouch/at5/comms/xC023_ac_status.py
pyairtouch/at5/comms/xC032_ac_timer_ctrl.py
pyairtouch/at5/comms/xC033_ac_timer_status.py
pyairtouch/at5/comms/xC0_ctrl_status.py
pyairtouch/comms/__init__.py
pyairtouch/comms/crc16.py
pyairtouch/comms/discovery.py
pyairtouch/comms/encoding.py
pyairtouch/comms/heartbeat.py
pyairtouch/comms/log.py
pyairtouch/comms/socket.py
pyairtouch/comms/udp.py
pyairtouch/factory.py
pyairtouch/py.typed
pyairtouch-3.1.0.dist-info/RECORD
