Metadata-Version: 2.1
Name: pyairtouch
Version: 3.1.0
Summary: A fully typed asyncio API for the Polyaire AirTouch AC controllers
Author-Email: TheNoctambulist <thenoctambulist@zoho.com>
License: MIT
Classifier: Development Status :: 5 - Production/Stable
Classifier: Intended Audience :: Developers
Classifier: Programming Language :: Python :: 3.11
Classifier: Programming Language :: Python :: 3.12
Classifier: Framework :: AsyncIO
Classifier: Typing :: Typed
Classifier: Operating System :: OS Independent
Classifier: License :: OSI Approved :: MIT License
Project-URL: Homepage, https://github.com/thenoctambulist/pyairtouch
Project-URL: Issues, https://github.com/thenoctambulist/pyairtouch/issues
Requires-Python: >=3.11
Requires-Dist: typing-extensions>=4.9.0
